backjoon/__init__.py
backjoon/bfs/__init__.py
backjoon/bfs/maze_search.py
backjoon/queue/__init__.py
backjoon/queue/queue.py
algorithm_hagyun-0.1.1.dist-info/METADATA
algorithm_hagyun-0.1.1.dist-info/WHEEL
algorithm_hagyun-0.1.1.dist-info/top_level.txt
algorithm_hagyun-0.1.1.dist-info/RECORD
